{
  "date": "2026-07-13",
  "products_added": [
    "MCP1ANT_Lora_1500_steps",
    "LingBot-30B-3B_GGUF_ComfyUI",
    "MOSS-TTS-Local-Transformer-v1.5-GGUF",
    "moss-tts-v1.5-8b-voice-acting",
    "whisper-small-finetuned-iwslt-irish-synthetic",
    "parakeet-tdt-0.6b-v3-gguf",
    "nemotron-3.5-asr-streaming-0.6b-gguf",
    "whisper-large-v3-turbo-mlx-8bit",
    "smt-grandstaff-GGUF"
  ],
  "major_updated": [],
  "glossary_added": [
    "MCP1ANT_Lora_1500_steps",
    "LingBot-30B-3B_GGUF_ComfyUI",
    "MOSS-TTS-Local-Transformer-v1.5-GGUF",
    "moss-tts-v1.5-8b-voice-acting",
    "whisper-small-finetuned-iwslt-irish-synthetic",
    "parakeet-tdt-0.6b-v3-gguf",
    "nemotron-3.5-asr-streaming-0.6b-gguf",
    "whisper-large-v3-turbo-mlx-8bit",
    "smt-grandstaff-GGUF"
  ],
  "products_ko_enriched": 0,
  "glossary_ko_enriched": 0,
  "errors": []
}