{
  "date": "2026-06-18",
  "products_added": [
    "ideogram_4_turbotime_lora",
    "wan2.2-ti2v-5b-mlx",
    "mms_e5_arm_a_real",
    "whisper-small-grpo-1fada6f-small-all50-blendreward-t0.7-lr3e-6-bs4",
    "whisper-medium-korean-500ksteps",
    "whisper-small_TLT_Finetuned_speed_augment",
    "whisper-klein-nl",
    "whisper-small_TLT_Finetuned_no_augment",
    "lightonocr-GGUF",
    "pix2struct-GGUF",
    "granite-vision-crispembed-GGUF",
    "PP-OCRv6_tiny_rec"
  ],
  "major_updated": [],
  "glossary_added": [
    "ideogram_4_turbotime_lora",
    "wan2.2-ti2v-5b-mlx",
    "mms_e5_arm_a_real",
    "whisper-small-grpo-1fada6f-small-all50-blendreward-t0.7-lr3e-6-bs4",
    "whisper-medium-korean-500ksteps",
    "whisper-small_TLT_Finetuned_speed_augment",
    "whisper-klein-nl",
    "whisper-small_TLT_Finetuned_no_augment",
    "lightonocr-GGUF",
    "pix2struct-GGUF",
    "granite-vision-crispembed-GGUF",
    "PP-OCRv6_tiny_rec"
  ],
  "products_ko_enriched": 2,
  "glossary_ko_enriched": 0,
  "errors": []
}